yai_nexus_configuration/__init__.py
yai_nexus_configuration/config.py
yai_nexus_configuration/decorator.py
yai_nexus_configuration/exceptions.py
yai_nexus_configuration/manager.py
yai_nexus_configuration/internal/store.py
yai_nexus_configuration/internal/utils.py
yai_nexus_configuration/internal/providers/__init__.py
yai_nexus_configuration/internal/providers/base.py
yai_nexus_configuration/internal/providers/file.py
yai_nexus_configuration/internal/providers/nacos.py
yai_nexus_configuration-0.1.1.dist-info/METADATA
yai_nexus_configuration-0.1.1.dist-info/WHEEL
yai_nexus_configuration-0.1.1.dist-info/top_level.txt
yai_nexus_configuration-0.1.1.dist-info/RECORD
