Metadata-Version: 2.4
Name: yai-nexus-configuration
Version: 0.1.1
Summary: 高质量的 Python 配置管理库 - 基于 Provider 模式，支持多种配置源
Author-email: YAI Team <team@yai.com>
Maintainer-email: YAI Team <team@yai.com>
License: MIT
Project-URL: Homepage, https://github.com/yai-team/yai-nexus-configuration
Project-URL: Documentation, https://yai-nexus-configuration.readthedocs.io/
Project-URL: Repository, https://github.com/yai-team/yai-nexus-configuration.git
Project-URL: Bug Tracker, https://github.com/yai-team/yai-nexus-configuration/issues
Project-URL: Changelog, https://github.com/yai-team/yai-nexus-configuration/blob/main/CHANGELOG.md
Keywords: configuration,config,nacos,apollo,settings,management,dynamic,provider,pydantic
Classifier: Development Status :: 4 - Beta
Classifier: Intended Audience :: Developers
Classifier: License :: OSI Approved :: MIT License
Classifier: Operating System :: OS Independent
Classifier: Programming Language :: Python :: 3
Classifier: Programming Language :: Python :: 3.8
Classifier: Programming Language :: Python :: 3.9
Classifier: Programming Language :: Python :: 3.10
Classifier: Programming Language :: Python :: 3.11
Classifier: Programming Language :: Python :: 3.12
Classifier: Topic :: Software Development :: Libraries :: Python Modules
Classifier: Topic :: System :: Systems Administration
Classifier: Topic :: Internet :: WWW/HTTP :: Dynamic Content
Requires-Python: >=3.8
Requires-Dist: pydantic<3.0.0,>=2.0.0
Requires-Dist: PyYAML<7.0.0,>=6.0.0
Provides-Extra: nacos
Requires-Dist: nacos-sdk-python<3.0.0,>=2.0.0; extra == "nacos"
Provides-Extra: test
Requires-Dist: pytest<8.0.0,>=7.0.0; extra == "test"
Requires-Dist: pytest-cov<5.0.0,>=4.0.0; extra == "test"
Requires-Dist: pytest-asyncio<1.0.0,>=0.21.0; extra == "test"
Provides-Extra: lint
Requires-Dist: black<24.0.0,>=23.0.0; extra == "lint"
Requires-Dist: isort<6.0.0,>=5.12.0; extra == "lint"
Requires-Dist: flake8<7.0.0,>=6.0.0; extra == "lint"
Requires-Dist: mypy<2.0.0,>=1.0.0; extra == "lint"
Requires-Dist: pre-commit>=3.0.0; extra == "lint"
Provides-Extra: docs
Requires-Dist: mkdocs>=1.4.0; extra == "docs"
Requires-Dist: mkdocs-material>=9.0.0; extra == "docs"
Requires-Dist: mkdocstrings[python]>=0.20.0; extra == "docs"
Provides-Extra: dev
Requires-Dist: yai-nexus-configuration[lint,test]; extra == "dev"
Provides-Extra: all
Requires-Dist: yai-nexus-configuration[dev,docs,nacos]; extra == "all"
